toolbox_continu_inzicht/__init__.py
toolbox_continu_inzicht/base/__init__.py
toolbox_continu_inzicht/base/aquo.py
toolbox_continu_inzicht/base/base_module.py
toolbox_continu_inzicht/base/config.py
toolbox_continu_inzicht/base/data_adapter.py
toolbox_continu_inzicht/base/exceedance_frequency_curve.py
toolbox_continu_inzicht/base/fragility_curve.py
toolbox_continu_inzicht/base/logging.py
toolbox_continu_inzicht/base/adapters/__init__.py
toolbox_continu_inzicht/base/adapters/data_adapter_utils.py
toolbox_continu_inzicht/base/adapters/load_data_adapters.py
toolbox_continu_inzicht/base/adapters/validate_dataframe.py
toolbox_continu_inzicht/base/adapters/input/__init__.py
toolbox_continu_inzicht/base/adapters/input/csv.py
toolbox_continu_inzicht/base/adapters/input/excel.py
toolbox_continu_inzicht/base/adapters/input/json.py
toolbox_continu_inzicht/base/adapters/input/netcdf.py
toolbox_continu_inzicht/base/adapters/input/postgresql.py
toolbox_continu_inzicht/base/adapters/input/python.py
toolbox_continu_inzicht/base/adapters/input/shape.py
toolbox_continu_inzicht/base/adapters/input/continu_inzicht_postgresql/__init__.py
toolbox_continu_inzicht/base/adapters/input/continu_inzicht_postgresql/input_fragilitycurve.py
toolbox_continu_inzicht/base/adapters/input/continu_inzicht_postgresql/input_general.py
toolbox_continu_inzicht/base/adapters/input/continu_inzicht_postgresql/input_impactanalyse.py
toolbox_continu_inzicht/base/adapters/input/continu_inzicht_postgresql/input_measuringstation.py
toolbox_continu_inzicht/base/adapters/input/continu_inzicht_postgresql/input_scenario.py
toolbox_continu_inzicht/base/adapters/input/continu_inzicht_postgresql/input_section.py
toolbox_continu_inzicht/base/adapters/input/flood_risk/__init__.py
toolbox_continu_inzicht/base/adapters/input/flood_risk/flood_risk_local_file.py
toolbox_continu_inzicht/base/adapters/input/flood_risk/readme.md
toolbox_continu_inzicht/base/adapters/output/__init__.py
toolbox_continu_inzicht-0.1.2.dist-info/METADATA
toolbox_continu_inzicht-0.1.2.dist-info/WHEEL
toolbox_continu_inzicht-0.1.2.dist-info/licenses/LICENSE
toolbox_continu_inzicht-0.1.2.dist-info/RECORD
