Metadata-Version: 2.4
Name: toolbox_continu_inzicht
Version: 0.1.2
Summary: Toolbox voor waterkeringbeheerders om risico's in kaart te brengen
Project-URL: Documentation, https://continu-inzicht.github.io/toolbox-continu-inzicht/
Project-URL: Source, https://github.com/continu-inzicht/toolbox-continu-inzicht
Author-email: David Haasnoot <d.haasnoot@hkv.nl>, Jerom Aerts <j.aerts@hkv.nl>, David Haasnoot <d.haasnoot@hkv.nl>, Guy Dupuits <dupuits@hkv.nl>, Bart Thonus <b.thonus@hkv.nl>, Rolf Waterman <r.watermans@hkv.nl>, Marit Zethof <m.zethof@hkv.nl>
License: GPL-3.0-or-later
License-File: LICENSE
Requires-Python: >=3.11
Requires-Dist: pandas
Requires-Dist: pydantic>=2
Requires-Dist: python-dotenv>=1.0.1
Requires-Dist: pyyaml
Provides-Extra: all
Requires-Dist: fiona; extra == 'all'
Requires-Dist: geopandas; extra == 'all'
Requires-Dist: httpx; extra == 'all'
Requires-Dist: netcdf4>=1.7.1; extra == 'all'
Requires-Dist: openpyxl; extra == 'all'
Requires-Dist: openturns>=1.23; extra == 'all'
Requires-Dist: probabilistic-piping==0.0.5; extra == 'all'
Requires-Dist: psycopg2; extra == 'all'
Requires-Dist: pyarrow; extra == 'all'
Requires-Dist: pydra-core==0.0.10; extra == 'all'
Requires-Dist: pyogrio; extra == 'all'
Requires-Dist: rasterstats>=0.20.0; extra == 'all'
Requires-Dist: requests; extra == 'all'
Requires-Dist: scipy; extra == 'all'
Requires-Dist: shapely; extra == 'all'
Requires-Dist: sqlalchemy; extra == 'all'
Requires-Dist: xarray; extra == 'all'
Provides-Extra: flood-scenarios
Requires-Dist: geopandas; extra == 'flood-scenarios'
Requires-Dist: rasterstats>=0.20.0; extra == 'flood-scenarios'
Requires-Dist: sqlalchemy; extra == 'flood-scenarios'
Provides-Extra: fragility-curves
Requires-Dist: openpyxl; extra == 'fragility-curves'
Requires-Dist: openturns>=1.23; extra == 'fragility-curves'
Requires-Dist: probabilistic-piping==0.0.5; extra == 'fragility-curves'
Requires-Dist: pydra-core==0.0.10; extra == 'fragility-curves'
Requires-Dist: scipy; extra == 'fragility-curves'
Provides-Extra: inspections
Requires-Dist: fiona; extra == 'inspections'
Requires-Dist: geopandas; extra == 'inspections'
Requires-Dist: httpx; extra == 'inspections'
Requires-Dist: netcdf4>=1.7.1; extra == 'inspections'
Requires-Dist: pyogrio; extra == 'inspections'
Requires-Dist: requests; extra == 'inspections'
Requires-Dist: shapely; extra == 'inspections'
Requires-Dist: sqlalchemy; extra == 'inspections'
Requires-Dist: xarray; extra == 'inspections'
Provides-Extra: io
Requires-Dist: netcdf4>=1.7.1; extra == 'io'
Requires-Dist: openpyxl; extra == 'io'
Requires-Dist: psycopg2; extra == 'io'
Requires-Dist: pyarrow; extra == 'io'
Requires-Dist: scipy; extra == 'io'
Requires-Dist: sqlalchemy; extra == 'io'
Requires-Dist: xarray; extra == 'io'
Provides-Extra: loads
Requires-Dist: geopandas; extra == 'loads'
Requires-Dist: httpx; extra == 'loads'
Requires-Dist: netcdf4>=1.7.1; extra == 'loads'
Requires-Dist: requests; extra == 'loads'
Requires-Dist: xarray; extra == 'loads'
Provides-Extra: sections
Requires-Dist: scipy; extra == 'sections'
